imio/__init__.py
imio/email/__init__.py
imio/email/parser/__init__.py
imio/email/parser/main.py
imio/email/parser/parser.py
imio/email/parser/utils.py
imio.email.parser-0.3.3.dist-info/METADATA
imio.email.parser-0.3.3.dist-info/WHEEL
imio.email.parser-0.3.3.dist-info/entry_points.txt
imio.email.parser-0.3.3.dist-info/top_level.txt
imio.email.parser-0.3.3.dist-info/RECORD
