Metadata-Version: 2.1
Name: imio.email.parser
Version: 0.3.3
Summary: This parser extracts forwarded attached email, embedded images and attachments. It also generates a PDF from the email.
Home-page: https://pypi.org/project/imio.email.parser
Author: Nicolas Demonté
Author-email: support@imio.be
License: GPL
Keywords: email parser pdf attachment
Classifier: Environment :: Console
Classifier: Environment :: No Input/Output (Daemon)
Classifier: Development Status :: 5 - Production/Stable
Classifier: Programming Language :: Python
Classifier: Programming Language :: Python :: 3
Classifier: Programming Language :: Python :: 3.10
Classifier: Operating System :: OS Independent
Classifier: License :: OSI Approved :: GNU General Public License v2 (GPLv2)
Requires-Python: >=3.10, <3.11
Requires-Dist: mail-parser
Requires-Dist: beautifulsoup4 >=4.6.3
Requires-Dist: email2pdf2
Requires-Dist: html5lib
Requires-Dist: lxml
Requires-Dist: pathvalidate
Requires-Dist: pypdf2
Requires-Dist: python-magic
Requires-Dist: reportlab
Requires-Dist: requests
Requires-Dist: six
Requires-Dist: tzlocal
